{
    "Stellantis": {"origin_block": "EU", "hq_country": "NL", "description": "Franco-Italian-American"},
    "Volkswagen Group": {"origin_block": "EU", "hq_country": "DE", "description": "German"},
    "Mercedes-Benz Group": {"origin_block": "EU", "hq_country": "DE", "description": "German"},
    "BMW Group": {"origin_block": "EU", "hq_country": "DE", "description": "German"},
    "Renault Group": {"origin_block": "EU", "hq_country": "FR", "description": "French"},
    "Toyota Group": {"origin_block": "JP", "hq_country": "JP", "description": "Japanese"},
    "Volvo Cars (Geely)": {"origin_block": "CN-owned", "hq_country": "SE", "description": "Chinese-owned (Geely)"},
    "AB Volvo (Trucks)": {"origin_block": "EU", "hq_country": "SE", "description": "Swedish"},
    "Hyundai-Kia": {"origin_block": "KR", "hq_country": "KR", "description": "Korean"},
    "Ford Motor": {"origin_block": "US", "hq_country": "US", "description": "American"},
    "Robert Bosch": {"origin_block": "EU", "hq_country": "DE", "description": "German"},
    "Continental AG": {"origin_block": "EU", "hq_country": "DE", "description": "German"},
    "ZF Friedrichshafen": {"origin_block": "EU", "hq_country": "DE", "description": "German"},
    "Valeo": {"origin_block": "EU", "hq_country": "FR", "description": "French"},
    "Forvia (Faurecia)": {"origin_block": "EU", "hq_country": "FR", "description": "French"},
    "Schaeffler": {"origin_block": "EU", "hq_country": "DE", "description": "German"},
    "STMicroelectronics": {"origin_block": "EU", "hq_country": "NL", "description": "Franco-Italian"},
    "Infineon": {"origin_block": "EU", "hq_country": "DE", "description": "German"},
    "NXP Semiconductors": {"origin_block": "EU", "hq_country": "NL", "description": "Dutch"},
    "Michelin": {"origin_block": "EU", "hq_country": "FR", "description": "French"},
    "Pirelli": {"origin_block": "EU", "hq_country": "IT", "description": "Italian (CN minority)"},
    "Bridgestone": {"origin_block": "JP", "hq_country": "JP", "description": "Japanese"},
    "Northvolt": {"origin_block": "EU", "hq_country": "SE", "description": "Swedish"},
    "ACC (Automotive Cells Company)": {"origin_block": "EU", "hq_country": "FR", "description": "Franco-German-Italian"},
    "Iveco Group": {"origin_block": "EU", "hq_country": "IT", "description": "Italian"},
    "Nissan": {"origin_block": "JP", "hq_country": "JP", "description": "Japanese"},
    "Honda": {"origin_block": "JP", "hq_country": "JP", "description": "Japanese"},
    "verkor": {"origin_block": "EU", "hq_country": "FR", "description": "French"},
    "FREYR": {"origin_block": "EU", "hq_country": "NO", "description": "Norwegian"},
    "Leclanch\u00e9": {"origin_block": "EU", "hq_country": "CH", "description": "Swiss"},
    "VARTA": {"origin_block": "EU", "hq_country": "DE", "description": "German"},
    "Samsung SDI": {"origin_block": "KR", "hq_country": "KR", "description": "Korean"},
    "SK Innovation": {"origin_block": "KR", "hq_country": "KR", "description": "Korean"},
    "LG Energy Solution": {"origin_block": "KR", "hq_country": "KR", "description": "Korean"},
    "Umicore": {"origin_block": "EU", "hq_country": "BE", "description": "Belgian"},
    "Johnson Matthey": {"origin_block": "EU", "hq_country": "GB", "description": "British"},
    "thyssenkrupp": {"origin_block": "EU", "hq_country": "DE", "description": "German"},
    "BASF": {"origin_block": "EU", "hq_country": "DE", "description": "German"},
    "Magna International": {"origin_block": "Other", "hq_country": "CA", "description": "Canadian"},
    "Denso": {"origin_block": "JP", "hq_country": "JP", "description": "Japanese"},
    "Aptiv": {"origin_block": "US", "hq_country": "US", "description": "American"},
    "CIE Automotive": {"origin_block": "EU", "hq_country": "ES", "description": "Spanish"},
    "Gestamp": {"origin_block": "EU", "hq_country": "ES", "description": "Spanish"},
    "Adient": {"origin_block": "US", "hq_country": "US", "description": "American"},
    "ZKW Group": {"origin_block": "KR", "hq_country": "AT", "description": "Korean (LG subsidiary)"},
    "Benteler": {"origin_block": "EU", "hq_country": "DE", "description": "German"},
    "CLN Group": {"origin_block": "EU", "hq_country": "IT", "description": "Italian"},
    "Horse Powertrain": {"origin_block": "EU", "hq_country": "ES", "description": "Franco-Chinese (Renault-Geely JV)"},
    "AGC Automotive": {"origin_block": "JP", "hq_country": "BE", "description": "Japanese"},
    "Rheinmetall": {"origin_block": "EU", "hq_country": "DE", "description": "German"},
    "Hella": {"origin_block": "EU", "hq_country": "DE", "description": "German (Faurecia subsidiary)"},
    "AVL": {"origin_block": "EU", "hq_country": "AT", "description": "Austrian"},
    "Vitesco Technologies": {"origin_block": "EU", "hq_country": "DE", "description": "German"},
    "Symbio (Faurecia/Michelin)": {"origin_block": "EU", "hq_country": "FR", "description": "Franco-German (Faurecia/Michelin JV)"},
    "OPmobility (Plastic Omnium)": {"origin_block": "EU", "hq_country": "FR", "description": "French"},
    "Solvay": {"origin_block": "EU", "hq_country": "BE", "description": "Belgian"},
    "InoBat Energy": {"origin_block": "EU", "hq_country": "SK", "description": "Slovak"},
    "Skeleton Technologies": {"origin_block": "EU", "hq_country": "EE", "description": "Estonian"},
    "ElringKlinger": {"origin_block": "EU", "hq_country": "DE", "description": "German"},
    "EKPO Fuel Cell Technologies": {"origin_block": "EU", "hq_country": "DE", "description": "German (EKPO = ElringKlinger + Plastic Omnium)"}
}
